tests/uv/__init__.py
tests/uv/fs/__init__.py
tests/uv/fs/test_fs.py
tests/uv/reader/__init__.py
tests/uv/reader/test_base.py
tests/uv/reader/test_store.py
tests/uv/reporter/__init__.py
tests/uv/reporter/test_base.py
tests/uv/reporter/test_state.py
tests/uv/reporter/test_store.py
tests/uv/sql/__init__.py
tests/uv/sql/test_sql.py
tests/uv/tensorflow/__init__.py
tests/uv/tensorflow/test_reporter.py
tests/uv/util/__init__.py
tests/uv/util/test_attachment.py
tests/uv/util/test_env.py
tests/uv/util/test_init.py
uv/__init__.py
uv/_version.py
uv/types.py
uv/fs/__init__.py
uv/fs/reader.py
uv/fs/reporter.py
uv/fs/util.py
uv/mlflow/__init__.py
uv/mlflow/reporter.py
uv/reader/__init__.py
uv/reader/base.py
uv/reader/store.py
uv/reporter/__init__.py
uv/reporter/base.py
uv/reporter/state.py
uv/reporter/store.py
uv/tensorflow/__init__.py
uv/tensorflow/reporter.py
uv/util/__init__.py
uv/util/attachment.py
uv/util/env.py
uv_metrics-0.4.2.dist-info/LICENSE
uv_metrics-0.4.2.dist-info/LICENSE_SHORT
uv_metrics-0.4.2.dist-info/METADATA
uv_metrics-0.4.2.dist-info/WHEEL
uv_metrics-0.4.2.dist-info/top_level.txt
uv_metrics-0.4.2.dist-info/RECORD
