Metadata-Version: 2.1
Name: uv-metrics
Version: 0.4.2
Summary: Shared tooling for Blueshift research.
Home-page: https://github.com/google/uv-metrics
Author: Sam Ritchie
Author-email: samritchie@google.com
License: Apache-2.0
Platform: UNKNOWN
Requires-Python: >=3.6.0
Requires-Dist: casfs (==0.1.1)
Requires-Dist: fs
Requires-Dist: fs-gcsfs
Requires-Dist: mlflow (==1.10.0)
Requires-Dist: numpy (>=1.18.0)
Requires-Dist: sqlalchemy
Requires-Dist: tqdm (>=4.42.1)
Provides-Extra: tf
Requires-Dist: tensorflow ; extra == 'tf'
Provides-Extra: tf-gpu
Requires-Dist: tensorflow-gpu ; extra == 'tf-gpu'
